dummygen_cli/__init__.py
dummygen_cli/dummygen_cli.py
dummygen_cli-0.1.3.dist-info/METADATA
dummygen_cli-0.1.3.dist-info/WHEEL
dummygen_cli-0.1.3.dist-info/top_level.txt
dummygen_cli-0.1.3.dist-info/RECORD
