Metadata-Version: 2.2
Name: dummygen-cli
Version: 0.1.3
Summary: A simple Python script to generate dummy file of specified size.
Home-page: https://github.com/karvanpy/dummygen-cli
Author: Ervan Kurniawan
Author-email: ervankurniawan41@gmail.com
Requires-Python: >=3.8
Requires-Dist: rich>=13.9.4
Dynamic: author
Dynamic: author-email
Dynamic: home-page
